mxcubecore/BaseHardwareObjects.py
mxcubecore/Command/BlueskyHttpServer.py
mxcubecore/Command/Epics.py
mxcubecore/Command/Exporter.py
mxcubecore/Command/Mockup.py
mxcubecore/Command/Pool.py
mxcubecore/Command/Sardana.py
mxcubecore/Command/Spec.py
mxcubecore/Command/Taco.py
mxcubecore/Command/Tango.py
mxcubecore/Command/Tine.py
mxcubecore/Command/__init__.py
mxcubecore/Command/exporter/ExporterClient.py
mxcubecore/Command/exporter/ExporterStates.py
mxcubecore/Command/exporter/MDEvents.py
mxcubecore/Command/exporter/StandardClient.py
mxcubecore/Command/exporter/__init__.py
mxcubecore/CommandContainer.py
mxcubecore/HardwareObjectFileParser.py
mxcubecore/HardwareObjects/ALBA/ALBAAutoProcessing.py
mxcubecore/HardwareObjects/ALBA/ALBABackLight.py
mxcubecore/HardwareObjects/ALBA/ALBABeamInfo.py
mxcubecore/HardwareObjects/ALBA/ALBACalibration.py
mxcubecore/HardwareObjects/ALBA/ALBACats.py
mxcubecore/HardwareObjects/ALBA/ALBACatsMaint.py
mxcubecore/HardwareObjects/ALBA/ALBAClusterJob.py
mxcubecore/HardwareObjects/ALBA/ALBACollect.py
mxcubecore/HardwareObjects/ALBA/ALBADataAnalysis.py
mxcubecore/HardwareObjects/ALBA/ALBAEnergy.py
mxcubecore/HardwareObjects/ALBA/ALBAEpsActuator.py
mxcubecore/HardwareObjects/ALBA/ALBAFastShutter.py
mxcubecore/HardwareObjects/ALBA/ALBAFlux.py
mxcubecore/HardwareObjects/ALBA/ALBAFrontEnd.py
mxcubecore/HardwareObjects/ALBA/ALBAFrontLight.py
mxcubecore/HardwareObjects/ALBA/ALBAISPyBClient.py
mxcubecore/HardwareObjects/ALBA/ALBAMachineInfo.py
mxcubecore/HardwareObjects/ALBA/ALBAMiniDiff.py
mxcubecore/HardwareObjects/ALBA/ALBAPilatus.py
mxcubecore/HardwareObjects/ALBA/ALBASession.py
mxcubecore/HardwareObjects/ALBA/ALBASupervisor.py
mxcubecore/HardwareObjects/ALBA/ALBATransmission.py
mxcubecore/HardwareObjects/ALBA/ALBAZoomMotor.py
mxcubecore/HardwareObjects/ALBA/ALBAZoomMotorAutoBrightness.py
mxcubecore/HardwareObjects/ALBA/XalocCalibration.py
mxcubecore/HardwareObjects/ALBA/XalocMachineInfo.py
mxcubecore/HardwareObjects/ALBA/XalocMiniDiff.py
mxcubecore-1.448.0.dist-info/METADATA
mxcubecore-1.448.0.dist-info/WHEEL
mxcubecore-1.448.0.dist-info/licenses/COPYING
mxcubecore-1.448.0.dist-info/licenses/COPYING.LESSER
mxcubecore-1.448.0.dist-info/RECORD
