Metadata-Version: 2.4
Name: mxcubecore
Version: 1.448.0
Summary: Core libraries for the MXCuBE application
License-Expression: LGPL-3.0-or-later
License-File: COPYING
License-File: COPYING.LESSER
Keywords: mxcube,mxcube3,mxcubecore
Author: The MXCuBE collaboration
Author-email: mxcube@esrf.fr
Maintainer: Marcus Oscarsson
Maintainer-email: mxcube@esrf.fr
Requires-Python: >=3.10,<3.12
Classifier: Development Status :: 5 - Production/Stable
Classifier: Intended Audience :: Developers
Classifier: Intended Audience :: Science/Research
Classifier: Intended Audience :: End Users/Desktop
Classifier: Natural Language :: English
Classifier: Topic :: Scientific/Engineering
Requires-Dist: Pillow (>=10.4.0,<11.0.0)
Requires-Dist: PyDispatcher (>=2.0.6,<3.0.0)
Requires-Dist: PyTango (>=9.3.6,<10.0.0)
Requires-Dist: colorama (>=0.4.6,<0.5.0)
Requires-Dist: defusedxml (==0.7.1)
Requires-Dist: f90nml (==1.3.1)
Requires-Dist: gevent (>=23.9.1,<24.0.0)
Requires-Dist: greenlet (>=3.0.3,<4.0.0)
Requires-Dist: jsonpickle (>=2.2.0,<3.0.0)
Requires-Dist: jsonschema (>=4.17.1,<5.0.0)
Requires-Dist: lucid3 (>=3.0.0,<4.0.0)
Requires-Dist: lxml (>=4.9.1,<5.0.0)
Requires-Dist: matplotlib (>=3.6.2,<4.0.0)
Requires-Dist: mxcube-video-streamer (>=1.8.4)
Requires-Dist: numpy (>=1.23.5,<2.0.0)
Requires-Dist: psutil (>=5.9.4,<6.0.0)
Requires-Dist: py4j (==0.10.9.9)
Requires-Dist: pydantic (>=2.8.2,<2.9.0)
Requires-Dist: python-ldap (>=3.4.5,<4.0.0)
Requires-Dist: requests (>=2.31.0,<3.0.0)
Requires-Dist: ruamel.yaml (>=0.17.21,<0.18.0)
Requires-Dist: scipy (>=1.9.3,<2.0.0)
Requires-Dist: suds-py3 (==1.4.5.0)
Requires-Dist: tomli (>=2.0.1,<3.0.0) ; python_full_version <= "3.10.0"
Requires-Dist: typing-extensions (>=4.3.0,<5.0.0)
Project-URL: Documentation, https://mxcubecore.readthedocs.io/
Project-URL: Homepage, https://github.com/mxcube/mxcubecore
Project-URL: Repository, https://github.com/mxcube/mxcubecore
